[{"id":1,"first_name":"Tedie","email":"tlardnar0@archive.org","book":"3000GT"},
{"id":2,"first_name":"Lizabeth","email":"ldoogue1@zdnet.com","book":"Golf"},
{"id":3,"first_name":"Bent","email":"bportch2@twitter.com","book":"TundraMax"},
{"id":4,"first_name":"Leisha","email":"ladamowicz3@mysql.com","book":"Tiburon"},
{"id":5,"first_name":"Meridel","email":"mzanetti4@google.ca","book":"Stratus"},
{"id":6,"first_name":"Coral","email":"cings5@sogou.com","book":"Esteem"},
{"id":7,"first_name":"Nydia","email":"nvern6@usnews.com","book":"Avalon"},
{"id":8,"first_name":"Brittany","email":"babramamov7@japanpost.jp","book":"Continental Flying Spur"},
{"id":9,"first_name":"Winnah","email":"wvokes8@about.me","book":"Silverado 2500"},
{"id":10,"first_name":"Erin","email":"edemalchar9@seesaa.net","book":"X-Type"}]